LICENSE
MANIFEST.in
README.rst
mongodict.py
setup.py
mongodict.egg-info/PKG-INFO
mongodict.egg-info/SOURCES.txt
mongodict.egg-info/dependency_links.txt
mongodict.egg-info/requires.txt
mongodict.egg-info/top_level.txt
mongodict.egg-info/zip-safe