Metadata-Version: 1.1
Name: mongodict
Version: 0.1.1
Summary: MongoDB-backed Python dict-like interface
Home-page: https://github.com/turicas/mongodict/
Author: Álvaro Justen
Author-email: alvarojusten@gmail.com
License: GPL3
Keywords: key-value,database,mongodb,dictionary
Platform: UNKNOWN
Classifier: Development Status :: 3 - Alpha
Classifier: Intended Audience :: Developers
Classifier: License :: OSI Approved :: GNU General Public License (GPL)
Classifier: Natural Language :: English
Classifier: Operating System :: OS Independent
Classifier: Programming Language :: Python :: 2.7
Classifier: Topic :: Software Development :: Libraries :: Python Modules
